{
    "structure": {
        "summary": "SUMMARY.md",
        "readme": "index.md"
    },
    "variables": {
        "products": [
            {
                "name": "Cocos Creator",
                "links": [
                    {
                        "name": "Manual",
                        "link": "http://docs.cocos.com/creator/manual/en"
                    },
                    {
                        "name": "API",
                        "link": "http://docs.cocos.com/creator/api/en"
                    }
                ]
            },
            {
                "name": "Cocos2d-x",
                "links": [
                    {
                        "name": "Manual",
                        "link": "http://docs.cocos.com/cocos2d-x/manual/en"
                    },
                    {
                        "name": "API",
                        "link": "http://www.cocos2d-x.org/docs/api-ref/index.html"
                    }
                ]
            },
            {
                "name": "AnySDK",
                "link": "http://docs.anysdk.com/"
            }
        ]
    }   
}